pyrtl/__init__.py
pyrtl/analysis.py
pyrtl/compilesim.py
pyrtl/conditional.py
pyrtl/core.py
pyrtl/corecircuits.py
pyrtl/helperfuncs.py
pyrtl/importexport.py
pyrtl/memory.py
pyrtl/passes.py
pyrtl/pyrtlexceptions.py
pyrtl/simulation.py
pyrtl/transform.py
pyrtl/visualization.py
pyrtl/wire.py
pyrtl/rtllib/__init__.py
pyrtl/rtllib/adders.py
pyrtl/rtllib/aes.py
pyrtl/rtllib/barrel.py
pyrtl/rtllib/libutils.py
pyrtl/rtllib/matrix.py
pyrtl/rtllib/multipliers.py
pyrtl/rtllib/muxes.py
pyrtl/rtllib/prngs.py
pyrtl/rtllib/testingutils.py
pyrtl-0.11.3.dist-info/METADATA
pyrtl-0.11.3.dist-info/WHEEL
pyrtl-0.11.3.dist-info/licenses/LICENSE.md
pyrtl-0.11.3.dist-info/RECORD
