Metadata-Version: 2.4
Name: pyrtl
Version: 0.11.3
Summary: RTL-level Hardware Design and Simulation Toolkit
Project-URL: Homepage, http://ucsbarchlab.github.io/PyRTL/
Project-URL: GitHub, https://github.com/UCSBarchlab/PyRTL
Project-URL: Documentation, https://pyrtl.readthedocs.io/
Project-URL: Changelog, https://github.com/UCSBarchlab/PyRTL/blob/development/CHANGELOG.md
Author: John Clow, UCSBarchlab
Author-email: Timothy Sherwood <sherwood@cs.ucsb.edu>
License: Copyright (c) 2015, Regents of the University of California
License-File: LICENSE.md
Classifier: Development Status :: 4 - Beta
Classifier: Environment :: Console
Classifier: Intended Audience :: Developers
Classifier: Intended Audience :: Education
Classifier: Intended Audience :: Science/Research
Classifier: License :: OSI Approved :: BSD License
Classifier: Natural Language :: English
Classifier: Operating System :: OS Independent
Classifier: Programming Language :: Python :: 3
Classifier: Topic :: Scientific/Engineering :: Electronic Design Automation (EDA)
Classifier: Topic :: System :: Hardware
Requires-Python: >=3.8
Provides-Extra: blif
Requires-Dist: pyparsing; extra == 'blif'
Provides-Extra: svg
Requires-Dist: graphviz; extra == 'svg'
